axon_drop-0.0.9.dist-info/licenses/LICENSE
drop/__init__.py
drop/_core.py
drop/_helpers.py
drop/_ops.py
drop/_random.py
drop/_scalar.py
drop/_tensor.py
drop/_utils.py
drop/nn.py
drop/build/libscalar.so
drop/build/libtensor.so
drop/csrc/cpu.cpp
drop/csrc/cpu.h
drop/csrc/dtype.cpp
drop/csrc/dtype.h
drop/csrc/main.cpp
drop/csrc/scalar.cpp
drop/csrc/scalar.h
drop/csrc/tensor.cpp
drop/csrc/tensor.h
axon_drop-0.0.9.dist-info/METADATA
axon_drop-0.0.9.dist-info/WHEEL
axon_drop-0.0.9.dist-info/top_level.txt
axon_drop-0.0.9.dist-info/RECORD
