Metadata-Version: 2.4
Name: axon-drop
Version: 0.0.9
Summary: Tensor manipulation library wrapped over a scalar-level autograd to compute backpropagation like PyTorch, but more like microgad
Author-email: shivendra <shivharsh44@gmail.com>
License-Expression: MIT
Classifier: Development Status :: 2 - Pre-Alpha
Classifier: Intended Audience :: Developers
Classifier: Programming Language :: C
Classifier: Programming Language :: C++
Classifier: Programming Language :: Python :: 3.8
Classifier: Programming Language :: Python :: 3.9
Classifier: Programming Language :: Python :: 3.10
Classifier: Programming Language :: Python :: 3.11
Classifier: Operating System :: OS Independent
License-File: LICENSE
Dynamic: license-file
